{"skeleton":{"hash":"lo9EIrNMd3Q3GoWHHBNgQisHrZY","spine":"3.8.99","images":"","audio":""},"bones":[{"name":"root"}],"slots":[{"name":"normal_a","bone":"root"},{"name":"normal_flag","bone":"root"},{"name":"normal_gloves","bone":"root"},{"name":"normal_j","bone":"root"},{"name":"normal_k","bone":"root"},{"name":"normal_q","bone":"root"},{"name":"normal_shoes","bone":"root"},{"name":"normal_soccerball","bone":"root"},{"name":"normal_soccerball_b","bone":"root"},{"name":"normal_ticket","bone":"root"},{"name":"normal_whistle","bone":"root"},{"name":"normal_10","bone":"root"}],"skins":[{"name":"default","attachments":{"normal_10":{"wh_vfx_b_normal_10_00000":{"width":150,"height":150},"wh_vfx_b_normal_10_00001":{"width":150,"height":150},"wh_vfx_b_normal_10_00002":{"width":150,"height":150},"wh_vfx_b_normal_10_00003":{"width":150,"height":150},"wh_vfx_b_normal_10_00004":{"width":150,"height":150}},"normal_a":{"wh_vfx_b_normal_a_00000":{"width":150,"height":150},"wh_vfx_b_normal_a_00001":{"width":150,"height":150},"wh_vfx_b_normal_a_00002":{"width":150,"height":150},"wh_vfx_b_normal_a_00003":{"width":150,"height":150},"wh_vfx_b_normal_a_00004":{"width":150,"height":150}},"normal_flag":{"wh_vfx_b_normal_flag_00000":{"width":150,"height":150},"wh_vfx_b_normal_flag_00001":{"width":150,"height":150},"wh_vfx_b_normal_flag_00002":{"width":150,"height":150},"wh_vfx_b_normal_flag_00003":{"width":150,"height":150},"wh_vfx_b_normal_flag_00004":{"width":150,"height":150}},"normal_gloves":{"wh_vfx_b_normal_gloves_00000":{"width":150,"height":150},"wh_vfx_b_normal_gloves_00001":{"width":150,"height":150},"wh_vfx_b_normal_gloves_00002":{"width":150,"height":150},"wh_vfx_b_normal_gloves_00003":{"width":150,"height":150},"wh_vfx_b_normal_gloves_00004":{"width":150,"height":150}},"normal_j":{"wh_vfx_b_normal_j_00000":{"width":150,"height":150},"wh_vfx_b_normal_j_00001":{"width":150,"height":150},"wh_vfx_b_normal_j_00002":{"width":150,"height":150},"wh_vfx_b_normal_j_00003":{"width":150,"height":150},"wh_vfx_b_normal_j_00004":{"width":150,"height":150}},"normal_k":{"wh_vfx_b_normal_k_00000":{"width":150,"height":150},"wh_vfx_b_normal_k_00001":{"width":150,"height":150},"wh_vfx_b_normal_k_00002":{"width":150,"height":150},"wh_vfx_b_normal_k_00003":{"width":150,"height":150},"wh_vfx_b_normal_k_00004":{"width":150,"height":150}},"normal_q":{"wh_vfx_b_normal_q_00000":{"width":150,"height":150},"wh_vfx_b_normal_q_00001":{"width":150,"height":150},"wh_vfx_b_normal_q_00002":{"width":150,"height":150},"wh_vfx_b_normal_q_00003":{"width":150,"height":150},"wh_vfx_b_normal_q_00004":{"width":150,"height":150}},"normal_shoes":{"wh_vfx_b_normal_shoes_00000":{"width":150,"height":150},"wh_vfx_b_normal_shoes_00001":{"width":150,"height":150},"wh_vfx_b_normal_shoes_00002":{"width":150,"height":150},"wh_vfx_b_normal_shoes_00003":{"width":150,"height":150},"wh_vfx_b_normal_shoes_00004":{"width":150,"height":150}},"normal_soccerball":{"wh_vfx_b_normal_soccerball_a_00000":{"width":150,"height":150},"wh_vfx_b_normal_soccerball_a_00001":{"width":150,"height":150},"wh_vfx_b_normal_soccerball_a_00002":{"width":150,"height":150},"wh_vfx_b_normal_soccerball_a_00003":{"width":150,"height":150},"wh_vfx_b_normal_soccerball_a_00004":{"width":150,"height":150}},"normal_soccerball_b":{"wh_vfx_b_normal_soccerball_b_00000":{"width":150,"height":150},"wh_vfx_b_normal_soccerball_b_00001":{"width":150,"height":150},"wh_vfx_b_normal_soccerball_b_00002":{"width":150,"height":150},"wh_vfx_b_normal_soccerball_b_00003":{"width":150,"height":150},"wh_vfx_b_normal_soccerball_b_00004":{"width":150,"height":150}},"normal_ticket":{"wh_vfx_b_normal_ticket_00000":{"width":150,"height":150},"wh_vfx_b_normal_ticket_00001":{"width":150,"height":150},"wh_vfx_b_normal_ticket_00002":{"width":150,"height":150},"wh_vfx_b_normal_ticket_00003":{"width":150,"height":150},"wh_vfx_b_normal_ticket_00004":{"width":150,"height":150}},"normal_whistle":{"wh_vfx_b_normal_whistle_00000":{"width":150,"height":150},"wh_vfx_b_normal_whistle_00001":{"width":150,"height":150},"wh_vfx_b_normal_whistle_00002":{"width":150,"height":150},"wh_vfx_b_normal_whistle_00003":{"width":150,"height":150},"wh_vfx_b_normal_whistle_00004":{"width":150,"height":150}}}}],"animations":{"normal_10":{"slots":{"normal_10":{"attachment":[{"name":"wh_vfx_b_normal_10_00000"},{"time":0.0333,"name":"wh_vfx_b_normal_10_00001"},{"time":0.0667,"name":"wh_vfx_b_normal_10_00002"},{"time":0.1,"name":"wh_vfx_b_normal_10_00003"},{"time":0.1333,"name":"wh_vfx_b_normal_10_00004"},{"time":0.1667,"name":null}]}}},"normal_a":{"slots":{"normal_a":{"attachment":[{"name":"wh_vfx_b_normal_a_00000"},{"time":0.0333,"name":"wh_vfx_b_normal_a_00001"},{"time":0.0667,"name":"wh_vfx_b_normal_a_00002"},{"time":0.1,"name":"wh_vfx_b_normal_a_00003"},{"time":0.1333,"name":"wh_vfx_b_normal_a_00004"},{"time":0.1667,"name":null}]}}},"normal_flag":{"slots":{"normal_flag":{"attachment":[{"name":"wh_vfx_b_normal_flag_00000"},{"time":0.0333,"name":"wh_vfx_b_normal_flag_00001"},{"time":0.0667,"name":"wh_vfx_b_normal_flag_00002"},{"time":0.1,"name":"wh_vfx_b_normal_flag_00003"},{"time":0.1333,"name":"wh_vfx_b_normal_flag_00004"},{"time":0.1667,"name":null}]}}},"normal_gloves":{"slots":{"normal_gloves":{"attachment":[{"name":"wh_vfx_b_normal_gloves_00000"},{"time":0.0333,"name":"wh_vfx_b_normal_gloves_00001"},{"time":0.0667,"name":"wh_vfx_b_normal_gloves_00002"},{"time":0.1,"name":"wh_vfx_b_normal_gloves_00003"},{"time":0.1333,"name":"wh_vfx_b_normal_gloves_00004"},{"time":0.1667,"name":null}]}}},"normal_j":{"slots":{"normal_j":{"attachment":[{"name":"wh_vfx_b_normal_j_00000"},{"time":0.0333,"name":"wh_vfx_b_normal_j_00001"},{"time":0.0667,"name":"wh_vfx_b_normal_j_00002"},{"time":0.1,"name":"wh_vfx_b_normal_j_00003"},{"time":0.1333,"name":"wh_vfx_b_normal_j_00004"},{"time":0.1667,"name":null}]}}},"normal_k":{"slots":{"normal_k":{"attachment":[{"name":"wh_vfx_b_normal_k_00000"},{"time":0.0333,"name":"wh_vfx_b_normal_k_00001"},{"time":0.0667,"name":"wh_vfx_b_normal_k_00002"},{"time":0.1,"name":"wh_vfx_b_normal_k_00003"},{"time":0.1333,"name":"wh_vfx_b_normal_k_00004"},{"time":0.1667,"name":null}]}}},"normal_q":{"slots":{"normal_q":{"attachment":[{"name":"wh_vfx_b_normal_q_00000"},{"time":0.0333,"name":"wh_vfx_b_normal_q_00001"},{"time":0.0667,"name":"wh_vfx_b_normal_q_00002"},{"time":0.1,"name":"wh_vfx_b_normal_q_00003"},{"time":0.1333,"name":"wh_vfx_b_normal_q_00004"},{"time":0.1667,"name":null}]}}},"normal_shoes":{"slots":{"normal_shoes":{"attachment":[{"name":"wh_vfx_b_normal_shoes_00000"},{"time":0.0333,"name":"wh_vfx_b_normal_shoes_00001"},{"time":0.0667,"name":"wh_vfx_b_normal_shoes_00002"},{"time":0.1,"name":"wh_vfx_b_normal_shoes_00003"},{"time":0.1333,"name":"wh_vfx_b_normal_shoes_00004"},{"time":0.1667,"name":null}]}}},"normal_soccerball_a":{"slots":{"normal_soccerball":{"attachment":[{"name":"wh_vfx_b_normal_soccerball_a_00000"},{"time":0.0667,"name":"wh_vfx_b_normal_soccerball_a_00002"},{"time":0.1,"name":"wh_vfx_b_normal_soccerball_a_00003"},{"time":0.1333,"name":"wh_vfx_b_normal_soccerball_a_00004"},{"time":0.1667,"name":null}]}}},"normal_soccerball_b":{"slots":{"normal_soccerball_b":{"attachment":[{"name":"wh_vfx_b_normal_soccerball_b_00000"},{"time":0.0333,"name":"wh_vfx_b_normal_soccerball_b_00001"},{"time":0.0667,"name":"wh_vfx_b_normal_soccerball_b_00002"},{"time":0.1,"name":"wh_vfx_b_normal_soccerball_b_00003"},{"time":0.1333,"name":"wh_vfx_b_normal_soccerball_b_00004"},{"time":0.1667,"name":null}]}}},"normal_ticket":{"slots":{"normal_ticket":{"attachment":[{"name":"wh_vfx_b_normal_ticket_00000"},{"time":0.0333,"name":"wh_vfx_b_normal_ticket_00001"},{"time":0.0667,"name":"wh_vfx_b_normal_ticket_00002"},{"time":0.1,"name":"wh_vfx_b_normal_ticket_00003"},{"time":0.1333,"name":"wh_vfx_b_normal_ticket_00004"},{"time":0.1667,"name":null}]}}},"normal_whistle":{"slots":{"normal_whistle":{"attachment":[{"name":"wh_vfx_b_normal_whistle_00000"},{"time":0.0333,"name":"wh_vfx_b_normal_whistle_00001"},{"time":0.0667,"name":"wh_vfx_b_normal_whistle_00002"},{"time":0.1,"name":"wh_vfx_b_normal_whistle_00003"},{"time":0.1333,"name":"wh_vfx_b_normal_whistle_00004"},{"time":0.1667,"name":null}]}}}}}